docling/__init__.py
docling/backend/__init__.py
docling/backend/abstract_backend.py
docling/backend/asciidoc_backend.py
docling/backend/csv_backend.py
docling/backend/docling_parse_backend.py
docling/backend/docling_parse_v2_backend.py
docling/backend/docling_parse_v4_backend.py
docling/backend/docx/__init__.py
docling/backend/docx/latex/__init__.py
docling/backend/docx/latex/latex_dict.py
docling/backend/docx/latex/omml.py
docling/backend/html_backend.py
docling/backend/json/__init__.py
docling/backend/json/docling_json_backend.py
docling/backend/md_backend.py
docling/backend/msexcel_backend.py
docling/backend/mspowerpoint_backend.py
docling/backend/msword_backend.py
docling/backend/pdf_backend.py
docling/backend/pypdfium2_backend.py
docling/backend/xml/__init__.py
docling/backend/xml/jats_backend.py
docling/backend/xml/uspto_backend.py
docling/chunking/__init__.py
docling/cli/__init__.py
docling/cli/main.py
docling/cli/models.py
docling/cli/tools.py
docling/datamodel/__init__.py
docling/datamodel/base_models.py
docling/datamodel/document.py
docling/datamodel/pipeline_options.py
docling/datamodel/settings.py
docling/document_converter.py
docling/exceptions.py
docling/models/__init__.py
docling/models/api_vlm_model.py
docling/models/base_model.py
docling/models/base_ocr_model.py
docling/models/code_formula_model.py
docling/models/document_picture_classifier.py
docling/models/easyocr_model.py
docling/models/factories/__init__.py
docling/models/factories/base_factory.py
docling/models/factories/ocr_factory.py
docling/models/factories/picture_description_factory.py
docling/models/hf_mlx_model.py
docling/models/hf_vlm_model.py
docling/models/layout_model.py
docling/models/ocr_mac_model.py
docling/models/page_assemble_model.py
docling/models/page_preprocessing_model.py
docling/models/picture_description_api_model.py
docling/models/picture_description_base_model.py
docling/models/picture_description_vlm_model.py
docling/models/plugins/__init__.py
docling_enhanced-2.32.0.dist-info/LICENSE
docling_enhanced-2.32.0.dist-info/METADATA
docling_enhanced-2.32.0.dist-info/WHEEL
docling_enhanced-2.32.0.dist-info/entry_points.txt
docling_enhanced-2.32.0.dist-info/RECORD
